README.md
setup.py
quantum_qubit_mapping/example.py
quantum_qubit_mapping.egg-info/PKG-INFO
quantum_qubit_mapping.egg-info/SOURCES.txt
quantum_qubit_mapping.egg-info/dependency_links.txt
quantum_qubit_mapping.egg-info/namespace_packages.txt
quantum_qubit_mapping.egg-info/top_level.txt
quantum_qubit_mapping/sabre_tools/__init__.py
quantum_qubit_mapping/sabre_tools/circuit_preprocess.py
quantum_qubit_mapping/sabre_tools/heuristic_function.py
quantum_qubit_mapping/sabre_tools/sabre.py