Metadata-Version: 2.1
Name: quantum-qubit-mapping
Version: 0.1.3
Summary: Qubit Mapping package and tools
Home-page: https://github.com/Kaustuvi/quantum-qubit_mapping
Author: Kaustuvi Basu, Petar Korponaić
Author-email: basu.kaustuvi@gmail.com, petar.korponaic@gmail.com
License: Apache License 2.0
Platform: UNKNOWN
Classifier: Development Status :: 4 - Beta
Classifier: License :: OSI Approved :: Apache Software License
Classifier: Programming Language :: Python :: 3
Classifier: Intended Audience :: Science/Research
